foo/__init__.py
foodemo-0.0.2.dist-info/LICENSE
foodemo-0.0.2.dist-info/METADATA
foodemo-0.0.2.dist-info/WHEEL
foodemo-0.0.2.dist-info/top_level.txt
foodemo-0.0.2.dist-info/RECORD
